{"metaInfo":{"dataIndex":"entityData","collectionName":"entities","responseObjectName":"response","apiCall":"appService"},"entities":[{"id":"b8e7eb8d-e51e-4e73-900d-0f20be521c0a","name":"All hair types","type":"dhairtype","domain":"referenceData","data":{"attributes":{"fkey":{"values":[{"value":"ht00","source":"internal","locale":"en-US"}]},"flabel":{"values":[{"value":"All hair types","source":"internal","locale":"en-US"}]},"ficonassetid":{"values":[{"value":"120391","source":"internal","locale":"en-US"}]},"ficonthumbnail":{"values":[{"value":"-120391.png","source":"internal","locale":"en-US"}]},"ficonmediacenterurl":{"values":[{"value":"http://mam.global.bdfgroup.net/#type=tree&categoryId=25909&assetId=120391","source":"internal","locale":"en-US"}]},"ficonsitecoreurl":{"values":[{"value":"/~/images/mam/-120391-1.png","source":"internal","locale":"en-US"}]}},"relationships":{}}},{"id":"16718716-7057-431d-a64b-be1560377def","name":"Normal hair","type":"dhairtype","domain":"referenceData","data":{"attributes":{"fkey":{"values":[{"value":"ht01","source":"internal","locale":"en-US"}]},"flabel":{"values":[{"value":"Normal hair","source":"internal","locale":"en-US"}]},"ficonassetid":{"values":[{"value":"120391","source":"internal","locale":"en-US"}]},"ficonthumbnail":{"values":[{"value":"-120391.png","source":"internal","locale":"en-US"}]},"ficonmediacenterurl":{"values":[{"value":"http://mam.global.bdfgroup.net/#type=tree&categoryId=25909&assetId=120391","source":"internal","locale":"en-US"}]},"ficonsitecoreurl":{"values":[{"value":"/~/images/mam/-120391-1.png","source":"internal","locale":"en-US"}]}},"relationships":{}}},{"id":"ca5f3ed7-c0e4-4e71-8bb7-18212aa071fb","name":"Coloured hair","type":"dhairtype","domain":"referenceData","data":{"attributes":{"fkey":{"values":[{"value":"ht02","source":"internal","locale":"en-US"}]},"flabel":{"values":[{"value":"Coloured hair","source":"internal","locale":"en-US"}]},"ficonassetid":{"values":[{"value":"120391","source":"internal","locale":"en-US"}]},"ficonthumbnail":{"values":[{"value":"-120391.png","source":"internal","locale":"en-US"}]},"ficonmediacenterurl":{"values":[{"value":"http://mam.global.bdfgroup.net/#type=tree&categoryId=25909&assetId=120391","source":"internal","locale":"en-US"}]},"ficonsitecoreurl":{"values":[{"value":"/~/images/mam/-120391-1.png","source":"internal","locale":"en-US"}]}},"relationships":{}}},{"id":"ad6d8dfc-665f-48b7-9dfc-2600a823a391","name":"Curly hair","type":"dhairtype","domain":"referenceData","data":{"attributes":{"fkey":{"values":[{"value":"ht03","source":"internal","locale":"en-US"}]},"flabel":{"values":[{"value":"Curly hair","source":"internal","locale":"en-US"}]},"ficonassetid":{"values":[{"value":"120391","source":"internal","locale":"en-US"}]},"ficonthumbnail":{"values":[{"value":"-120391.png","source":"internal","locale":"en-US"}]},"ficonmediacenterurl":{"values":[{"value":"http://mam.global.bdfgroup.net/#type=tree&categoryId=25909&assetId=120391","source":"internal","locale":"en-US"}]},"ficonsitecoreurl":{"values":[{"value":"/~/images/mam/-120391-1.png","source":"internal","locale":"en-US"}]}},"relationships":{}}},{"id":"92435884-fc33-44bc-a0db-e6812ee6a49f","name":"Damaged hair","type":"dhairtype","domain":"referenceData","data":{"attributes":{"fkey":{"values":[{"value":"ht04","source":"internal","locale":"en-US"}]},"flabel":{"values":[{"value":"Damaged hair","source":"internal","locale":"en-US"}]},"ficonassetid":{"values":[{"value":"120391","source":"internal","locale":"en-US"}]},"ficonthumbnail":{"values":[{"value":"-120391.png","source":"internal","locale":"en-US"}]},"ficonmediacenterurl":{"values":[{"value":"http://mam.global.bdfgroup.net/#type=tree&categoryId=25909&assetId=120391","source":"internal","locale":"en-US"}]},"ficonsitecoreurl":{"values":[{"value":"/~/images/mam/-120391-1.png","source":"internal","locale":"en-US"}]}},"relationships":{}}},{"id":"5e845c9a-7c0c-4a4c-be81-8d3377d723c2","name":"Dandruff","type":"dhairtype","domain":"referenceData","data":{"attributes":{"fkey":{"values":[{"value":"ht05","source":"internal","locale":"en-US"}]},"flabel":{"values":[{"value":"Dandruff","source":"internal","locale":"en-US"}]},"ficonassetid":{"values":[{"value":"120391","source":"internal","locale":"en-US"}]},"ficonthumbnail":{"values":[{"value":"-120391.png","source":"internal","locale":"en-US"}]},"ficonmediacenterurl":{"values":[{"value":"http://mam.global.bdfgroup.net/#type=tree&categoryId=25909&assetId=120391","source":"internal","locale":"en-US"}]},"ficonsitecoreurl":{"values":[{"value":"/~/images/mam/-120391-1.png","source":"internal","locale":"en-US"}]}},"relationships":{}}},{"id":"7252db42-8c69-4b3f-9a9f-fa537bbdd569","name":"Greasy hair","type":"dhairtype","domain":"referenceData","data":{"attributes":{"fkey":{"values":[{"value":"ht06","source":"internal","locale":"en-US"}]},"flabel":{"values":[{"value":"Greasy hair","source":"internal","locale":"en-US"}]},"ficonassetid":{"values":[{"value":"120391","source":"internal","locale":"en-US"}]},"ficonthumbnail":{"values":[{"value":"-120391.png","source":"internal","locale":"en-US"}]},"ficonmediacenterurl":{"values":[{"value":"http://mam.global.bdfgroup.net/#type=tree&categoryId=25909&assetId=120391","source":"internal","locale":"en-US"}]},"ficonsitecoreurl":{"values":[{"value":"/~/images/mam/-120391-1.png","source":"internal","locale":"en-US"}]}},"relationships":{}}},{"id":"1ea74785-6124-423a-8ca4-faf5403a4854","name":"Fine/flat hair","type":"dhairtype","domain":"referenceData","data":{"attributes":{"fkey":{"values":[{"value":"ht07","source":"internal","locale":"en-US"}]},"flabel":{"values":[{"value":"Fine/flat hair","source":"internal","locale":"en-US"}]},"ficonassetid":{"values":[{"value":"120391","source":"internal","locale":"en-US"}]},"ficonthumbnail":{"values":[{"value":"-120391.png","source":"internal","locale":"en-US"}]},"ficonmediacenterurl":{"values":[{"value":"http://mam.global.bdfgroup.net/#type=tree&categoryId=25909&assetId=120391","source":"internal","locale":"en-US"}]},"ficonsitecoreurl":{"values":[{"value":"/~/images/mam/-120391-1.png","source":"internal","locale":"en-US"}]}},"relationships":{}}},{"id":"a89056d6-ea9f-440a-af71-015cd89994af","name":"Dry hair","type":"dhairtype","domain":"referenceData","data":{"attributes":{"fkey":{"values":[{"value":"ht08","source":"internal","locale":"en-US"}]},"flabel":{"values":[{"value":"Dry hair","source":"internal","locale":"en-US"}]},"ficonassetid":{"values":[{"value":"120391","source":"internal","locale":"en-US"}]},"ficonthumbnail":{"values":[{"value":"-120391.png","source":"internal","locale":"en-US"}]},"ficonmediacenterurl":{"values":[{"value":"http://mam.global.bdfgroup.net/#type=tree&categoryId=25909&assetId=120391","source":"internal","locale":"en-US"}]},"ficonsitecoreurl":{"values":[{"value":"/~/images/mam/-120391-1.png","source":"internal","locale":"en-US"}]}},"relationships":{}}},{"id":"77e053c6-4e8e-45bf-a9ac-7aa498892a25","name":"Thick hair","type":"dhairtype","domain":"referenceData","data":{"attributes":{"fkey":{"values":[{"value":"ht09","source":"internal","locale":"en-US"}]},"flabel":{"values":[{"value":"Thick hair","source":"internal","locale":"en-US"}]},"ficonassetid":{"values":[{"value":"120391","source":"internal","locale":"en-US"}]},"ficonthumbnail":{"values":[{"value":"-120391.png","source":"internal","locale":"en-US"}]},"ficonmediacenterurl":{"values":[{"value":"http://mam.global.bdfgroup.net/#type=tree&categoryId=25909&assetId=120391","source":"internal","locale":"en-US"}]},"ficonsitecoreurl":{"values":[{"value":"/~/images/mam/-120391-1.png","source":"internal","locale":"en-US"}]}},"relationships":{}}}]}